[{"state":1,"opération":"mise à jour","date_":"2024-06-09T22:24:39.470Z"},{"state":0,"opération":"mise à jour","date_":"2024-06-09T22:24:47.918Z"},{"prenom":"pierro","nom":"kalala","post_nom":"tshibangu","date_naissance":"2000-10-10","lieu_naissance":"kananga","email":"lelo@gmail.com","telephone":"testtest","adresse_physique":"gombe","opération":"mise à jour","date_":"2024-06-10T06:51:37.590Z"},{"prenom":"pierr","nom":"kalala","post_nom":"tshibangu","date_naissance":"2000-10-10","lieu_naissance":"kananga","email":"lelo@gmail.com","telephone":"testtest","adresse_physique":"gombe","opération":"mise à jour","date_":"2024-06-10T06:57:55.493Z"},{"prenom":"pierrot","nom":"kalala","post_nom":"tshibangu","date_naissance":"2000-10-10","lieu_naissance":"kananga","email":"lelo@gmail.com","telephone":"testtest","adresse_physique":"gombe","opération":"mise à jour","date_":"2024-06-10T06:58:54.094Z"},{"prenom":"pierroquet","nom":"kalala","post_nom":"tshibangu","date_naissance":"2000-10-10","lieu_naissance":"kananga","email":"lelo@gmail.com","telephone":"testtest","adresse_physique":"gombe","opération":"mise à jour","date_":"2024-06-10T06:59:09.509Z"},{"prenom":"pierroqu","nom":"kalala","post_nom":"tshibangu","date_naissance":"2000-10-10","lieu_naissance":"kananga","email":"lelo@gmail.com","telephone":"testtest","adresse_physique":"gombe","opération":"mise à jour","date_":"2024-06-10T07:01:52.431Z"},{"prenom":"pierro","nom":"kalala","post_nom":"tshibangu","date_naissance":"2000-10-10","lieu_naissance":"kananga","email":"lelo@gmail.com","telephone":"testtest","adresse_physique":"gombe","opération":"mise à jour","date_":"2024-06-10T07:03:47.071Z"},{"prenom":"pierrot","nom":"kalala","post_nom":"tshibangu","date_naissance":"2000-10-10","lieu_naissance":"kananga","email":"lelo@gmail.com","telephone":"testtest","adresse_physique":"gombe","opération":"mise à jour","date_":"2024-06-10T07:04:17.340Z"},{"state":0,"opération":"mise à jour","id_user":130,"date_":"2024-06-13T13:43:54.588Z"},{"state":1,"opération":"mise à jour","id_user":130,"date_":"2024-06-13T14:04:18.194Z"},{"state":0,"opération":"mise à jour","id_user":130,"date_":"2024-06-13T14:10:21.674Z"},{"state":1,"opération":"mise à jour","id_user":130,"date_":"2024-06-15T10:32:04.978Z"},{"state":0,"opération":"mise à jour","id_user":130,"date_":"2024-06-15T10:32:16.408Z"},{"state":1,"opération":"mise à jour","id_user":130,"date_":"2024-06-15T10:32:17.586Z"},{"prenom":"benoit","nom":"zechel","post_nom":"kross","date_naissance":"1999-11-12","lieu_naissance":"kisangani","email":"benoit@gmail.cd","telephone":"+243810000","adresse_physique":"30 juin","opération":"mise à jour","id_user":130,"date_":"2024-06-21T23:31:28.956Z"},{"prenom":"benoit","nom":"zechel","post_nom":"kross","date_naissance":"1999-11-12","lieu_naissance":"kisangani","email":"benoit@gmail.cd","telephone":"+243810000000","adresse_physique":"30 juin","opération":"mise à jour","id_user":130,"date_":"2024-06-21T23:38:38.615Z"},{"prenom":"benoit","nom":"zechel","post_nom":"kross","date_naissance":"1999-11-12","lieu_naissance":"kisangani","email":"benoit@gmail.cd","telephone":"+243810000002","adresse_physique":"30 juin","opération":"mise à jour","id_user":130,"date_":"2024-06-21T23:39:20.517Z"}]